cequest/__init__.py
cequest/exceptions.py
cequest/model.py
cequest/req.py
cequest/sess.py
cequest-0.0.1.dist-info/WHEEL
cequest-0.0.1.dist-info/METADATA
cequest-0.0.1.dist-info/RECORD
