Metadata-Version: 2.1
Name: cequest
Version: 0.0.1
Summary: Advanced python-based request library with proxy support, exception handling & more.
Author: ecriminals
Author-email: bio@fbi.ac
Requires-Python: >=3.10.0,<3.11
Classifier: Programming Language :: Python :: 3
Classifier: Programming Language :: Python :: 3.10
Requires-Dist: Brotli (>=1.0.9,<2.0.0)
Requires-Dist: Flask (>=2.2.0,<3.0.0)
Requires-Dist: numpy (>=1.22.2,<2.0.0)
Requires-Dist: replit (>=3.2.4,<4.0.0)
Requires-Dist: selenium (>=4.8.2,<5.0.0)
Requires-Dist: urllib3 (>=1.26.12,<2.0.0)
